retrieval_tool_selector/__init__.py
retrieval_tool_selector/core.py
retrieval_tool_selector-0.1.0.dist-info/licenses/LICENSE
retrieval_tool_selector-0.1.0.dist-info/METADATA
retrieval_tool_selector-0.1.0.dist-info/WHEEL
retrieval_tool_selector-0.1.0.dist-info/top_level.txt
retrieval_tool_selector-0.1.0.dist-info/RECORD
