Metadata-Version: 2.4
Name: retrieval-tool-selector
Version: 0.1.0
Summary: Retrieval-augmented tool selector for semantic API matching
Home-page: https://github.com/xiaoyesoso/retrieval-tool-selector
Author: SoulJoy（卓寿杰）
Author-email: zhuoshoujie@126.com
Classifier: Programming Language :: Python :: 3
Classifier: License :: OSI Approved :: MIT License
Classifier: Operating System :: OS Independent
Requires-Python: >=3.8
License-File: LICENSE
Requires-Dist: openai>=1.0.0
Requires-Dist: numpy>=1.20.0
Requires-Dist: scikit-learn>=1.0.0
Dynamic: author
Dynamic: author-email
Dynamic: classifier
Dynamic: description
Dynamic: description-content-type
Dynamic: home-page
Dynamic: license-file
Dynamic: requires-dist
Dynamic: requires-python
Dynamic: summary
